Workbook

Sheet One Time Cost
B2: UNIT 2: Systems Planning | PLANNING ESTIMATES (PHP)
C5: BREAKDOWN OF ONE TIME COST WORKSHEET
C7: Assumed project development duration: 3 MONTHS (part-time project fees)
C9: A. Development Cost
J10: BREAKDOWN OF ONE TIME COST WORKSHEET
C12: Description | D12: Fee/Month | F12: Mo. | G12: Sub_Total
J14: A. Development Cost | L14: =IF(ISNUMBER('One Time Cost'!$G$22),'One Time Cost'!$G$22,"") -> 107000
C15: System Analyst (PT) | D15: 10000 | F15: 3 | G15: =IF(COUNT('One Time Cost'!$D$15,'One Time Cost'!$F$15)=2,'One Time Cost'!$D$15*'One Time Cost'!$F$15,"") -> 30000
J16: B. User Training | L16: =IF(ISNUMBER('One Time Cost'!$H$32),'One Time Cost'!$H$32,"") -> 4000
C17: Programmer (PT) | D17: 20000 | F17: 3 | G17: =IF(COUNT('One Time Cost'!$D$17,'One Time Cost'!$F$17)=2,'One Time Cost'!$D$17*'One Time Cost'!$F$17,"") -> 60000
J18: C. Additional Hardware/Software | L18: =IF(ISNUMBER('One Time Cost'!$H$49),'One Time Cost'!$H$49,"") -> 3500
C19: Encoder (PT) | D19: 5000 | F19: 1 | G19: =IF(COUNT('One Time Cost'!$D$19,'One Time Cost'!$F$19)=2,'One Time Cost'!$D$19*'One Time Cost'!$F$19,"") -> 5000
C20: Research / QA (PT) | D20: 6000 | F20: 2 | G20: =IF(COUNT('One Time Cost'!$D$20,'One Time Cost'!$F$20)=2,'One Time Cost'!$D$20*'One Time Cost'!$F$20,"") -> 12000
J21: TOTAL ONE TIME COST | L21: =IF(COUNT('One Time Cost'!$G$22,'One Time Cost'!$H$32,'One Time Cost'!$H$49)=3,SUM('One Time Cost'!$G$22,'One Time Cost'!$H$32,'One Time Cost'!$H$49),"") -> 114500
C22: TOTAL | G22: =IF(COUNT('One Time Cost'!$G$15,'One Time Cost'!$G$17,'One Time Cost'!$G$19,'One Time Cost'!$G$20)=4,SUM('One Time Cost'!$G$15,'One Time Cost'!$G$17,'One Time Cost'!$G$19,'One Time Cost'!$G$20),"") -> 107000
J23: Total One Time Cost = Total Development Cost + Total User Training + Total Additional Hardware/Software
C25: B. User Training
C28: Description | E28: Honoraria/day | H28: Sub_Total
C29: User Training (2 days) | E29: 1500 | H29: =IF(COUNT('One Time Cost'!$E$29,'Input Details'!$C$7)=2,'One Time Cost'!$E$29*'Input Details'!$C$7,"") -> 3000
C30: Training Kit | E30: 1000 | H30: =IF(ISNUMBER('One Time Cost'!$E$30),'One Time Cost'!$E$30,"") -> 1000
J31: RECURRING COST
C32: TOTAL | H32: =IF(COUNT('One Time Cost'!$H$29,'One Time Cost'!$H$30)=2,SUM('One Time Cost'!$H$29,'One Time Cost'!$H$30),"") -> 4000
J34: Description | K34: Rate (PHP) | N34: Annually
J36: Software Maintenance | K36: 750 | N36: =IF(ISNUMBER('One Time Cost'!$K$36),'One Time Cost'!$K$36*12,"") -> 9000
C37: C. ADDITIONAL HARDWARE/SOFTWARE
J38: Cloud Database + Storage | K38: =IF(COUNT('Input Details'!$C$12,'Input Details'!$C$11)=2,'Input Details'!$C$12*'Input Details'!$C$11,"") -> 1625 | N38: =IF(ISNUMBER('One Time Cost'!$K$38),'One Time Cost'!$K$38*12,"") -> 19500
J40: Static Frontend Hosting | K40: 0 | N40: =IF(ISNUMBER('One Time Cost'!$K$40),'One Time Cost'!$K$40*12,"") -> 0
C41: Description | E41: Unit Cost | H41: Sub_Total
J42: Incremental Communication | K42: 200 | N42: =IF(ISNUMBER('One Time Cost'!$K$42),'One Time Cost'!$K$42*12,"") -> 2400
C43: Cloud Database Setup | E43: 1000 | H43: =IF(COUNT('One Time Cost'!$E$43,'Input Details'!$C$8)=2,'One Time Cost'!$E$43*'Input Details'!$C$8,"") -> 1000
J44: Domain Renewal (year) | K44: 900 | N44: =IF(ISNUMBER('One Time Cost'!$K$44),'One Time Cost'!$K$44*1,"") -> 900
C45: External Drive | E45: 2500 | H45: =IF(COUNT('One Time Cost'!$E$45,'Input Details'!$C$9)=2,'One Time Cost'!$E$45*'Input Details'!$C$9,"") -> 2500
J46: Software License Renewal | K46: 0 | N46: =IF(ISNUMBER('One Time Cost'!$K$46),'One Time Cost'!$K$46*1,"") -> 0
C47: Open-source Tools / Free SSL | E47: 0 | H47: =IF(COUNT('One Time Cost'!$E$47,'Input Details'!$C$10)=2,'One Time Cost'!$E$47*'Input Details'!$C$10,"") -> 0
J48: TOTAL | N48: =IF(COUNT('One Time Cost'!$N$36,'One Time Cost'!$N$38,'One Time Cost'!$N$40,'One Time Cost'!$N$42,'One Time Cost'!$N$44,'One Time Cost'!$N$46)=6,SUM('One Time Cost'!$N$36,'One Time Cost'!$N$38,'One Time Cost'!$N$40,'One Time Cost'!$N$42,'One Time Cost'!$N$44,'One Time Cost'!$N$46),"") -> 31800
C49: TOTAL | H49: =IF(COUNT('One Time Cost'!$H$43,'One Time Cost'!$H$45,'One Time Cost'!$H$47)=3,SUM('One Time Cost'!$H$43,'One Time Cost'!$H$45,'One Time Cost'!$H$47),"") -> 3500
N52: PHP EST.
C53: Total One Time Cost = Total Development Cost + Total User Training + Total Additional Hardware/Software
B58: All financial figures are planning estimates in PHP, not actual company expenses. Maintenance, hosting and communication rates are monthly; renewals are annual. Free or bundled items are explicitly shown as 0.00. See Planning Basis for assumptions and sources.
B60: IT303: SYSTEMS ANALYSIS AND DESIGN | P60: 1

Sheet Cost Explanation
B2: UNIT 2: Systems Planning | PLANNING ESTIMATES (PHP)
C4: Training Kit | D4: =IF(ISNUMBER('One Time Cost'!$E$30),'One Time Cost'!$E$30,"") -> 1000 | E4: =IF(ISNUMBER('One Time Cost'!$H$30),'One Time Cost'!$H$30,"") -> 1000 | G4: Description | H4: Rate (PHP) | J4: Annually
C5: TOTAL | E5: =IF(ISNUMBER('One Time Cost'!$H$32),'One Time Cost'!$H$32,"") -> 4000 | G5: Software Maintenance | H5: =IF(ISNUMBER('One Time Cost'!$K$36),'One Time Cost'!$K$36,"") -> 750 | J5: =IF(ISNUMBER('One Time Cost'!$N$36),'One Time Cost'!$N$36,"") -> 9000
G6: Cloud Database + Storage | H6: =IF(ISNUMBER('One Time Cost'!$K$38),'One Time Cost'!$K$38,"") -> 1625 | J6: =IF(ISNUMBER('One Time Cost'!$N$38),'One Time Cost'!$N$38,"") -> 19500
G8: Static Frontend Hosting | H8: =IF(ISNUMBER('One Time Cost'!$K$40),'One Time Cost'!$K$40,"") -> 0 | J8: =IF(ISNUMBER('One Time Cost'!$N$40),'One Time Cost'!$N$40,"") -> 0
C9: C. ADDITIONAL HARDWARE/SOFTWARE
G10: Incremental Communication | H10: =IF(ISNUMBER('One Time Cost'!$K$42),'One Time Cost'!$K$42,"") -> 200 | J10: =IF(ISNUMBER('One Time Cost'!$N$42),'One Time Cost'!$N$42,"") -> 2400
G12: Domain Renewal (year) | H12: =IF(ISNUMBER('One Time Cost'!$K$44),'One Time Cost'!$K$44,"") -> 900 | J12: =IF(ISNUMBER('One Time Cost'!$N$44),'One Time Cost'!$N$44,"") -> 900
C13: Description | D13: Unit Cost | E13: Sub_Total
G14: Software License Renewal | H14: =IF(ISNUMBER('One Time Cost'!$K$46),'One Time Cost'!$K$46,"") -> 0 | J14: =IF(ISNUMBER('One Time Cost'!$N$46),'One Time Cost'!$N$46,"") -> 0
C15: Cloud Database Setup | D15: =IF(ISNUMBER('One Time Cost'!$E$43),'One Time Cost'!$E$43,"") -> 1000 | E15: =IF(ISNUMBER('One Time Cost'!$H$43),'One Time Cost'!$H$43,"") -> 1000
G16: TOTAL | J16: =IF(ISNUMBER('One Time Cost'!$N$48),'One Time Cost'!$N$48,"") -> 31800
C17: External Drive | D17: =IF(ISNUMBER('One Time Cost'!$E$45),'One Time Cost'!$E$45,"") -> 2500 | E17: =IF(ISNUMBER('One Time Cost'!$H$45),'One Time Cost'!$H$45,"") -> 2500
C19: Open-source Tools / Free SSL | D19: =IF(ISNUMBER('One Time Cost'!$E$47),'One Time Cost'!$E$47,"") -> 0 | E19: =IF(ISNUMBER('One Time Cost'!$H$47),'One Time Cost'!$H$47,"") -> 0
C20: TOTAL | E20: =IF(ISNUMBER('One Time Cost'!$H$49),'One Time Cost'!$H$49,"") -> 3500
C22: Total One Time Cost = Total Development Cost + Total User Training + Total Additional Hardware/Software
J23: PHP EST.
B28: The estimated one-time investment is PHP 114,500.00: development PHP 107,000.00, user training PHP 4,000.00, and deployment/backup hardware PHP 3,500.00. Estimated annual recurring cost is PHP 31,800.00. These figures form a planning scenario and are not actual company spending or approved vendor quotations.
B30: The green company monitoring table records 758 units across 26 equipment categories. It identifies 19 round shovels, 75 GI pipes and 369 swivel clamps under “Missing or No Report,” totaling 463 units. These are reconciliation gaps; the table does not establish confirmed financial losses.
B32: Estimated annual operational value is PHP 80,290.00, comprising PHP 4,690.00 in supplies cash savings and PHP 75,600.00 in released staff capacity. The capacity value is not payroll savings. Supplies savings alone do not cover the PHP 31,800.00 yearly running cost; the net cash requirement remains PHP 27,110.00 per year.
B34: IT303: SYSTEMS ANALYSIS AND DESIGN | L34: 2

Sheet Tangible Benefits
B2: UNIT 2: Systems Planning | PLANNING ESTIMATES (PHP)
C4: • Benefit
C7: Breakdown of Tangible Benefit Worksheet
C8: A. SUPPLIES COST
C10: EXISTING SYSTEM | K10: PROPOSED SYSTEM
C11: Description | D11: Qty | F11: Price/Qty | H11: Sub_Total | K11: Description | L11: Qty | N11: Price/Qty | Q11: Sub_Total
C12: Folders (bundle) | D12: 4 | F12: 150 | H12: =IF(COUNT('Tangible Benefits'!$D$12,'Tangible Benefits'!$F$12)=2,'Tangible Benefits'!$D$12*'Tangible Benefits'!$F$12,"") -> 600 | K12: Folders (bundle) | L12: 2 | N12: 150 | Q12: =IF(COUNT('Tangible Benefits'!$L$12,'Tangible Benefits'!$N$12)=2,'Tangible Benefits'!$L$12*'Tangible Benefits'!$N$12,"") -> 300
C13: Ballpen (box) | D13: 3 | F13: 150 | H13: =IF(COUNT('Tangible Benefits'!$D$13,'Tangible Benefits'!$F$13)=2,'Tangible Benefits'!$D$13*'Tangible Benefits'!$F$13,"") -> 450 | K13: Ballpen (box) | L13: 2 | N13: 150 | Q13: =IF(COUNT('Tangible Benefits'!$L$13,'Tangible Benefits'!$N$13)=2,'Tangible Benefits'!$L$13*'Tangible Benefits'!$N$13,"") -> 300
C14: Bond Papers (ream) | D14: 12 | F14: 250 | H14: =IF(COUNT('Tangible Benefits'!$D$14,'Tangible Benefits'!$F$14)=2,'Tangible Benefits'!$D$14*'Tangible Benefits'!$F$14,"") -> 3000 | K14: Bond Papers (ream) | L14: 4 | N14: 250 | Q14: =IF(COUNT('Tangible Benefits'!$L$14,'Tangible Benefits'!$N$14)=2,'Tangible Benefits'!$L$14*'Tangible Benefits'!$N$14,"") -> 1000
C15: Carbon Paper (pack) | D15: 1 | F15: 150 | H15: =IF(COUNT('Tangible Benefits'!$D$15,'Tangible Benefits'!$F$15)=2,'Tangible Benefits'!$D$15*'Tangible Benefits'!$F$15,"") -> 150 | K15: Record Book (pc) | L15: 2 | N15: 80 | Q15: =IF(COUNT('Tangible Benefits'!$L$15,'Tangible Benefits'!$N$15)=2,'Tangible Benefits'!$L$15*'Tangible Benefits'!$N$15,"") -> 160
C16: Record Book (pc) | D16: 6 | F16: 80 | H16: =IF(COUNT('Tangible Benefits'!$D$16,'Tangible Benefits'!$F$16)=2,'Tangible Benefits'!$D$16*'Tangible Benefits'!$F$16,"") -> 480 | K16: USB (piece) | L16: 0 | N16: 400 | Q16: =IF(COUNT('Tangible Benefits'!$L$16,'Tangible Benefits'!$N$16)=2,'Tangible Benefits'!$L$16*'Tangible Benefits'!$N$16,"") -> 0
C17: Vouchers (pad) | D17: 12 | F17: 60 | H17: =IF(COUNT('Tangible Benefits'!$D$17,'Tangible Benefits'!$F$17)=2,'Tangible Benefits'!$D$17*'Tangible Benefits'!$F$17,"") -> 720 | K17: Ink (bottle) | L17: 3 | N17: 350 | Q17: =IF(COUNT('Tangible Benefits'!$L$17,'Tangible Benefits'!$N$17)=2,'Tangible Benefits'!$L$17*'Tangible Benefits'!$N$17,"") -> 1050
C18: Ink (bottle) | D18: 6 | F18: 350 | H18: =IF(COUNT('Tangible Benefits'!$D$18,'Tangible Benefits'!$F$18)=2,'Tangible Benefits'!$D$18*'Tangible Benefits'!$F$18,"") -> 2100
C19: TOTAL | H19: =IF(COUNT('Tangible Benefits'!$H$12,'Tangible Benefits'!$H$13,'Tangible Benefits'!$H$14,'Tangible Benefits'!$H$15,'Tangible Benefits'!$H$16,'Tangible Benefits'!$H$17,'Tangible Benefits'!$H$18)=7,SUM('Tangible Benefits'!$H$12,'Tangible Benefits'!$H$13,'Tangible Benefits'!$H$14,'Tangible Benefits'!$H$15,'Tangible Benefits'!$H$16,'Tangible Benefits'!$H$17,'Tangible Benefits'!$H$18),"") -> 7500 | K19: TOTAL | Q19: =IF(COUNT('Tangible Benefits'!$Q$12,'Tangible Benefits'!$Q$13,'Tangible Benefits'!$Q$14,'Tangible Benefits'!$Q$15,'Tangible Benefits'!$Q$16,'Tangible Benefits'!$Q$17)=6,SUM('Tangible Benefits'!$Q$12,'Tangible Benefits'!$Q$13,'Tangible Benefits'!$Q$14,'Tangible Benefits'!$Q$15,'Tangible Benefits'!$Q$16,'Tangible Benefits'!$Q$17),"") -> 2810
C21: Supplies Cost Reduction = Total Supplies of the Existing System − Total Supplies of the Proposed System
C22: Supplies Cost Reduction | P22: =IF(COUNT('Tangible Benefits'!$H$19,'Tangible Benefits'!$Q$19)=2,'Tangible Benefits'!$H$19-'Tangible Benefits'!$Q$19,"") -> 4690
C24: B. LABOR AND PRODUCTIVITY VALUE
C26: EXISTING SYSTEM | K26: PROPOSED SYSTEM
C27: Activity | E27: Allocated Cost/ Month | G27: Annual | K27: Activity | M27: Allocated Cost/ Month | O27: Annual
C28: Inventory monitoring | E28: =IF(COUNT('Input Details'!$C$14,'Input Details'!$C$13)=2,'Input Details'!$C$14*'Input Details'!$C$13,"") -> 6000 | G28: =IF(ISNUMBER('Tangible Benefits'!$E$28),'Tangible Benefits'!$E$28*12,"") -> 72000 | K28: Inventory monitoring | M28: =IF(COUNT('Input Details'!$C$17,'Input Details'!$C$13)=2,'Input Details'!$C$17*'Input Details'!$C$13,"") -> 3000 | O28: =IF(ISNUMBER('Tangible Benefits'!$M$28),'Tangible Benefits'!$M$28*12,"") -> 36000
C29: Report preparation | E29: =IF(COUNT('Input Details'!$C$15,'Input Details'!$C$13)=2,'Input Details'!$C$15*'Input Details'!$C$13,"") -> 2400 | G29: =IF(ISNUMBER('Tangible Benefits'!$E$29),'Tangible Benefits'!$E$29*12,"") -> 28800 | K29: Report preparation | M29: =IF(COUNT('Input Details'!$C$18,'Input Details'!$C$13)=2,'Input Details'!$C$18*'Input Details'!$C$13,"") -> 900 | O29: =IF(ISNUMBER('Tangible Benefits'!$M$29),'Tangible Benefits'!$M$29*12,"") -> 10800
C30: Reconciliation / follow-up | E30: =IF(COUNT('Input Details'!$C$16,'Input Details'!$C$13)=2,'Input Details'!$C$16*'Input Details'!$C$13,"") -> 3600 | G30: =IF(ISNUMBER('Tangible Benefits'!$E$30),'Tangible Benefits'!$E$30*12,"") -> 43200 | K30: Reconciliation / follow-up | M30: =IF(COUNT('Input Details'!$C$19,'Input Details'!$C$13)=2,'Input Details'!$C$19*'Input Details'!$C$13,"") -> 1800 | O30: =IF(ISNUMBER('Tangible Benefits'!$M$30),'Tangible Benefits'!$M$30*12,"") -> 21600
C31: TOTAL | G31: =IF(COUNT('Tangible Benefits'!$G$28,'Tangible Benefits'!$G$29,'Tangible Benefits'!$G$30)=3,SUM('Tangible Benefits'!$G$28,'Tangible Benefits'!$G$29,'Tangible Benefits'!$G$30),"") -> 144000 | K31: TOTAL | O31: =IF(COUNT('Tangible Benefits'!$O$28,'Tangible Benefits'!$O$29,'Tangible Benefits'!$O$30)=3,SUM('Tangible Benefits'!$O$28,'Tangible Benefits'!$O$29,'Tangible Benefits'!$O$30),"") -> 68400
C33: Productivity Value = Existing Allocated Labor Cost − Proposed Allocated Labor Cost
C34: Labor Productivity Value | P34: =IF(COUNT('Tangible Benefits'!$G$31,'Tangible Benefits'!$O$31)=2,'Tangible Benefits'!$G$31-'Tangible Benefits'!$O$31,"") -> 75600
C36: Total Annual Tangible Value = Productivity Value + Supplies Cash Savings
C37: Total Annual Tangible Value | P37: =IF(COUNT('Tangible Benefits'!$P$34,'Tangible Benefits'!$P$22)=2,SUM('Tangible Benefits'!$P$34,'Tangible Benefits'!$P$22),"") -> 80290
B40: Estimated annual supplies spending falls from PHP 7,500.00 to PHP 2,810.00, a potential cash saving of PHP 4,690.00. Allocated labor falls from PHP 144,000.00 to PHP 68,400.00, releasing capacity valued at PHP 75,600.00 per year. Combined tangible value is PHP 80,290.00; no salary or headcount reduction is assumed.
B42: No equipment-loss or recovery saving is credited (PHP 0.00). The 463 missing or unreported units remain a reconciliation concern, not confirmed losses. A USB purchase is unnecessary in this scenario because cloud reporting and the separately budgeted backup drive are available; its subtotal is PHP 0.00.
B44: IT303: SYSTEMS ANALYSIS AND DESIGN | S44: 3

Sheet Company Inventory
B2: HAND TOOLS AND OTHERS MONITORING
B4: ITEM NO. | C4: POWER TOOLS | D4: QTY. | E4: NEED TO COMPLY | F4: MISSING OR NO REPORT
B5: 1 | C5: SHOVEL (PALA, LAPAD) | D5: 19 | E5: — | F5: —
B6: 2 | C6: SHOVEL (PALA, BILOG) | D6: 23 | E6: 42 | F6: 19
B7: 3 | C7: BARETA | D7: 13 | E7: — | F7: —
B8: 4 | C8: ITAK | D8: 4 | E8: — | F8: —
B9: 5 | C9: PIKO | D9: 4 | E9: — | F9: —
B10: 6 | C10: PLASTIC DRUM 200L | D10: 14 | E10: — | F10: —
B11: 7 | C11: IBC WATER TANK 1000L | D11: 5 | E11: — | F11: —
B12: 8 | C12: WHEEL BARROW | D12: 4 | E12: — | F12: —
B13: 9 | C13: OXYGEN TANK | D13: 3 | E13: — | F13: —
B14: 10 | C14: GAS TANK | D14: 5 | E14: — | F14: —
B15: 11 | C15: ELECTRIC KETTLE | D15: 2 | E15: — | F15: —
B16: 12 | C16: EXTENSION | D16: 10 | E16: — | F16: —
B17: 13 | C17: DOUBLE BURNER STOVE | D17: 8 | E17: — | F17: —
B18: 14 | C18: LABABO | D18: 5 | E18: — | F18: —
... B20: 16 | C20: GARDEN HOSE | D20: 5 | E20: — | F20: —
B21: 17 | C21: GI PIPES | D21: 225 | E21: 300 | F21: 75
B22: 18 | C22: BASE JACK | D22: 27 | E22: — | F22: —
B23: 19 | C23: U-JACK | D23: 56 | E23: — | F23: —
B24: 20 | C24: BUCKETS | D24: 39 | E24: — | F24: —
B25: 21 | C25: CATWALK FLATFORM SCAFFOLDING | D25: 33 | E25: — | F25: —
B26: 22 | C26: H-FRAME SCAFFOLDING | D26: 64 | E26: — | F26: —
B27: 23 | C27: BRACES SCAFFOLDING | D27: 41 | E27: — | F27: —
B28: 24 | C28: WATER-PUMP | D28: 2 | E28: — | F28: —
B29: 25 | C29: GARDEN SPRINKLER | D29: 2 | E29: — | F29: —
B30: 26 | C30: SWIVEL CLAMP | D30: 141 | E30: 510 | F30: 369
B32: SOURCE CHECK: 26 populated categories; 758 recorded units; 463 missing or unreported units.
B34: A dash means not reported in the source, not zero. Only three categories have supplied requirements and gaps. The 463 units are not confirmed physical losses. “CATWALK FLATFORM SCAFFOLDING” preserves the source spelling; unused row 27 is omitted.
B36: Source: user-supplied green “HAND TOOLS AND OTHERS MONITORING” image. Application records are demonstration data and are excluded.
B38: COMPANY DATA SOURCE: GREEN INVENTORY TABLE ONLY | H38: 4

Sheet Input Details
B2: PLANNING BASIS — EDITABLE ESTIMATES (PHP)
B4: These financial values and task timings are illustrative estimates, not actual company expenses. Only the green inventory quantities are company data. A three-month build is assumed; project fees cover part-time services.
B6: Supporting input | C6: Estimate | D6: Unit / basis
B7: Training duration | C7: 2 | D7: days
B8: Cloud deployment setup quantity | C8: 1 | D8: setup service
B9: External backup drive quantity | C9: 1 | D9: one drive
B10: Open-source / SSL package quantity | C10: 1 | D10: free package
B11: Planning exchange rate | C11: 65 | D11: PHP per USD
B12: Hosted backend subscription | C12: 25 | D12: USD per month [S1]
B13: Administrative time valuation | C13: 150 | D13: PHP per person-hour
B14: Existing inventory-monitoring time | C14: 40 | D14: person-hours per month
B15: Existing report-preparation time | C15: 16 | D15: person-hours per month
B16: Existing reconciliation / follow-up time | C16: 24 | D16: person-hours per month
B17: Proposed inventory-monitoring time | C17: 20 | D17: person-hours per month
B18: Proposed report-preparation time | C18: 6 | D18: person-hours per month
B19: Proposed reconciliation / follow-up time | C19: 12 | D19: person-hours per month
B21: Cost boundaries: coding/testing is covered by the development retainers; PHP 1,000 setup covers account provisioning and deployment checks. The backup drive is a separate offline export copy. Hosted database storage and bundled database backups are paid once; frontend hosting, open-source licenses and SSL add no separate fee.
B23: Labor basis: estimated monthly task time falls from 80 to 38 person-hours. The 42 hours released each month equal 504 hours/year; at PHP 150/hour, productivity value is PHP 75,600/year. This does not reduce payroll. Supplies savings are PHP 4,690/year; after PHP 31,800 recurring costs, net cash impact is negative PHP 27,110/year.
B25: BENCHMARKS AND SOURCES — CHECKED 24 OCTOBER 2026
B27: [S1] Supabase Pro: USD 25/month starting price, within stated quotas. https://supabase.com/pricing
B29: [S2] Cloudflare Pages Free: static hosting limits apply. https://developers.cloudflare.com/pages/platform/limits/
B31: [S3] Registrar: no-markup domain pricing and included SSL. PHP 900 is an allowance. https://www.cloudflare.com/domains/
B33: [S4] Philippine wage context only; company wages are unknown. https://nwpc.dole.gov.ph/ncr/
B35: [S5] Official FX reference. PHP 65/USD is a rounded planning conversion. https://www.bsp.gov.ph/SitePages/Statistics/exchangerate.aspx
B37: Other rates, supplies quantities, hardware allowance and time reductions are analyst estimates, not quotations. Training includes a basic two-day orientation; any additional paid participant overtime needs a revised budget. Confirm taxes, actual usage and remaining development scope before spending.
B39: PLANNING ESTIMATES; COMPANY SOURCE: GREEN INVENTORY TABLE ONLY | F39: 5
