Workbook

Sheet One Time Cost
B2: UNIT 2: Systems Planning
C5: BREAKDOWN OF ONE TIME COST WORKSHEET
C7: Assuming that the project development duration is ______ MONTHS
C9: A. Development Cost
I10: BREAKDOWN OF ONE TIME COST WORKSHEET
C12: Description | D12: Salary/Month | E12: Mo. | G12: Sub_Total
I14: A. Development Cost | K14: =IF(ISNUMBER('One Time Cost'!$G$22),'One Time Cost'!$G$22,"")
C15: System Analyst | G15: =IF(COUNT('One Time Cost'!$D$15,'One Time Cost'!$E$15)=2,'One Time Cost'!$D$15*'One Time Cost'!$E$15,"")
I16: B. User Training | K16: =IF(ISNUMBER('One Time Cost'!$F$32),'One Time Cost'!$F$32,"")
C17: Programmer | G17: =IF(COUNT('One Time Cost'!$D$17,'One Time Cost'!$E$17)=2,'One Time Cost'!$D$17*'One Time Cost'!$E$17,"")
I18: C. Additional Hardware/Software | K18: =IF(ISNUMBER('One Time Cost'!$F$47),'One Time Cost'!$F$47,"")
C19: Encoder | G19: =IF(COUNT('One Time Cost'!$D$19,'One Time Cost'!$E$19)=2,'One Time Cost'!$D$19*'One Time Cost'!$E$19,"")
C20: Researcher | G20: =IF(COUNT('One Time Cost'!$D$20,'One Time Cost'!$E$20)=2,'One Time Cost'!$D$20*'One Time Cost'!$E$20,"")
I21: TOTAL ONE TIME COST | K21: =IF(COUNT('One Time Cost'!$G$22,'One Time Cost'!$F$32,'One Time Cost'!$F$47)=3,SUM('One Time Cost'!$G$22,'One Time Cost'!$F$32,'One Time Cost'!$F$47),"")
C22: TOTAL | G22: =IF(COUNT('One Time Cost'!$G$15,'One Time Cost'!$G$17,'One Time Cost'!$G$19,'One Time Cost'!$G$20)=4,SUM('One Time Cost'!$G$15,'One Time Cost'!$G$17,'One Time Cost'!$G$19,'One Time Cost'!$G$20),"")
I23: Total One Time Cost = Total Development Cost + Total User Training + Total Additional Hardware/Software
C25: B. User Training
C28: Description | D28: Honoraria/day | F28: Sub_Total
C29: User Training | F29: =IF(COUNT('One Time Cost'!$D$29,'Input Details'!$C$7)=2,'One Time Cost'!$D$29*'Input Details'!$C$7,"")
C30: Training Kit | F30: =IF(ISNUMBER('One Time Cost'!$D$30),'One Time Cost'!$D$30,"")
I31: RECURRING COST
C32: TOTAL | F32: =IF(COUNT('One Time Cost'!$F$29,'One Time Cost'!$F$30)=2,SUM('One Time Cost'!$F$29,'One Time Cost'!$F$30),"")
I34: Description | J34: Unit Cost | M34: Annually
I36: Software Maintenance | M36: =IF(ISNUMBER('One Time Cost'!$J$36),'One Time Cost'!$J$36*12,"")
C37: C. ADDITIONAL HARDWARE/SOFTWARE
I38: Incremental Communication | M38: =IF(ISNUMBER('One Time Cost'!$J$38),'One Time Cost'!$J$38*12,"")
I40: Software License Renewal | M40: =IF(ISNUMBER('One Time Cost'!$J$40),'One Time Cost'!$J$40*1,"")
C41: Description | D41: Unit Cost | F41: Sub_Total
I42: TOTAL | M42: =IF(COUNT('One Time Cost'!$M$36,'One Time Cost'!$M$38,'One Time Cost'!$M$40)=3,SUM('One Time Cost'!$M$36,'One Time Cost'!$M$38,'One Time Cost'!$M$40),"")
C43: Database Server | F43: =IF(COUNT('One Time Cost'!$D$43,'Input Details'!$C$8)=2,'One Time Cost'!$D$43*'Input Details'!$C$8,"")
C45: External Drive | F45: =IF(COUNT('One Time Cost'!$D$45,'Input Details'!$C$9)=2,'One Time Cost'!$D$45*'Input Details'!$C$9,"")
C46: Licensed Software / Vendor Platform | F46: =IF(COUNT('One Time Cost'!$D$46,'Input Details'!$C$10)=2,'One Time Cost'!$D$46*'Input Details'!$C$10,"")
C47: TOTAL | F47: =IF(COUNT('One Time Cost'!$F$43,'One Time Cost'!$F$45,'One Time Cost'!$F$46)=3,SUM('One Time Cost'!$F$43,'One Time Cost'!$F$45,'One Time Cost'!$F$46),"")
C50: Total One Time Cost = Total Development Cost + Total User Training + Total Additional Hardware/Software
B54: Financial amounts and development duration are blank because the green company inventory table does not supply them. Monthly maintenance/communication and annual renewal are worksheet billing units, not purchased services.
B56: IT303: SYSTEMS ANALYSIS AND DESIGN | O56: 1

Sheet Cost Explanation
B2: UNIT 2: Systems Planning
C4: Training Kit | D4: =IF(ISNUMBER('One Time Cost'!$D$30),'One Time Cost'!$D$30,"") | E4: =IF(ISNUMBER('One Time Cost'!$F$30),'One Time Cost'!$F$30,"") | G4: Description | H4: Unit Cost | J4: Annually
C5: TOTAL | E5: =IF(ISNUMBER('One Time Cost'!$F$32),'One Time Cost'!$F$32,"") | G5: Software Maintenance | H5: =IF(ISNUMBER('One Time Cost'!$J$36),'One Time Cost'!$J$36,"") | J5: =IF(ISNUMBER('One Time Cost'!$M$36),'One Time Cost'!$M$36,"")
G6: Incremental Communication | H6: =IF(ISNUMBER('One Time Cost'!$J$38),'One Time Cost'!$J$38,"") | J6: =IF(ISNUMBER('One Time Cost'!$M$38),'One Time Cost'!$M$38,"")
G8: Software License Renewal | H8: =IF(ISNUMBER('One Time Cost'!$J$40),'One Time Cost'!$J$40,"") | J8: =IF(ISNUMBER('One Time Cost'!$M$40),'One Time Cost'!$M$40,"")
C9: C. ADDITIONAL HARDWARE/SOFTWARE
G10: TOTAL | J10: =IF(ISNUMBER('One Time Cost'!$M$42),'One Time Cost'!$M$42,"")
C13: Description | D13: Unit Cost | E13: Sub_Total
C14: Database Server | D14: =IF(ISNUMBER('One Time Cost'!$D$43),'One Time Cost'!$D$43,"") | E14: =IF(ISNUMBER('One Time Cost'!$F$43),'One Time Cost'!$F$43,"")
C15: External Drive | D15: =IF(ISNUMBER('One Time Cost'!$D$45),'One Time Cost'!$D$45,"") | E15: =IF(ISNUMBER('One Time Cost'!$F$45),'One Time Cost'!$F$45,"")
C16: Licensed Software / Vendor Platform | D16: =IF(ISNUMBER('One Time Cost'!$D$46),'One Time Cost'!$D$46,"") | E16: =IF(ISNUMBER('One Time Cost'!$F$46),'One Time Cost'!$F$46,"")
C17: TOTAL | E17: =IF(ISNUMBER('One Time Cost'!$F$47),'One Time Cost'!$F$47,"")
C19: Total One Time Cost = Total Development Cost + Total User Training + Total Additional Hardware/Software
B23: This table follows the Breakdown of One Time Cost Worksheet in the supplied academic reference. The total one-time cost of PHP __________ will serve as the initial investment, and the annual recurring cost of PHP __________ will represent additional system expenses. These amounts are left blank because company financial data has not been supplied.
B25: The green company monitoring table records 758 units across 26 equipment categories. It identifies 19 round shovels, 75 GI pipes and 369 swivel clamps under “Missing or No Report,” totaling 463 units. These are reconciliation gaps; the table does not establish confirmed financial losses.
B27: IT303: SYSTEMS ANALYSIS AND DESIGN | L27: 2

Sheet Tangible Benefits
B2: UNIT 2: Systems Planning
C4: • Benefit
C7: Breakdown of Tangible Benefit Worksheet
C8: A. SUPPLIES COST
C10: EXISTING SYSTEM | K10: PROPOSED SYSTEM
C11: Description | D11: Qty | F11: Price/Qty | H11: Sub_Total | K11: Description | L11: Qty | N11: Price/Qty | Q11: Sub_Total
C12: Folders | H12: =IF(COUNT('Tangible Benefits'!$D$12,'Tangible Benefits'!$F$12)=2,'Tangible Benefits'!$D$12*'Tangible Benefits'!$F$12,"") | K12: Folders | Q12: =IF(COUNT('Tangible Benefits'!$L$12,'Tangible Benefits'!$N$12)=2,'Tangible Benefits'!$L$12*'Tangible Benefits'!$N$12,"")
C13: Ballpen | H13: =IF(COUNT('Tangible Benefits'!$D$13,'Tangible Benefits'!$F$13)=2,'Tangible Benefits'!$D$13*'Tangible Benefits'!$F$13,"") | K13: Ballpen | Q13: =IF(COUNT('Tangible Benefits'!$L$13,'Tangible Benefits'!$N$13)=2,'Tangible Benefits'!$L$13*'Tangible Benefits'!$N$13,"")
C14: Bond Papers | H14: =IF(COUNT('Tangible Benefits'!$D$14,'Tangible Benefits'!$F$14)=2,'Tangible Benefits'!$D$14*'Tangible Benefits'!$F$14,"") | K14: Bond Papers | Q14: =IF(COUNT('Tangible Benefits'!$L$14,'Tangible Benefits'!$N$14)=2,'Tangible Benefits'!$L$14*'Tangible Benefits'!$N$14,"")
C15: Carbon Papers | H15: =IF(COUNT('Tangible Benefits'!$D$15,'Tangible Benefits'!$F$15)=2,'Tangible Benefits'!$D$15*'Tangible Benefits'!$F$15,"") | K15: Record Book | Q15: =IF(COUNT('Tangible Benefits'!$L$15,'Tangible Benefits'!$N$15)=2,'Tangible Benefits'!$L$15*'Tangible Benefits'!$N$15,"")
C16: Record Book | H16: =IF(COUNT('Tangible Benefits'!$D$16,'Tangible Benefits'!$F$16)=2,'Tangible Benefits'!$D$16*'Tangible Benefits'!$F$16,"") | K16: USB | Q16: =IF(COUNT('Tangible Benefits'!$L$16,'Tangible Benefits'!$N$16)=2,'Tangible Benefits'!$L$16*'Tangible Benefits'!$N$16,"")
C17: Vouchers | H17: =IF(COUNT('Tangible Benefits'!$D$17,'Tangible Benefits'!$F$17)=2,'Tangible Benefits'!$D$17*'Tangible Benefits'!$F$17,"") | K17: Ink | Q17: =IF(COUNT('Tangible Benefits'!$L$17,'Tangible Benefits'!$N$17)=2,'Tangible Benefits'!$L$17*'Tangible Benefits'!$N$17,"")
C18: Ink | H18: =IF(COUNT('Tangible Benefits'!$D$18,'Tangible Benefits'!$F$18)=2,'Tangible Benefits'!$D$18*'Tangible Benefits'!$F$18,"")
C19: TOTAL | H19: =IF(COUNT('Tangible Benefits'!$H$12,'Tangible Benefits'!$H$13,'Tangible Benefits'!$H$14,'Tangible Benefits'!$H$15,'Tangible Benefits'!$H$16,'Tangible Benefits'!$H$17,'Tangible Benefits'!$H$18)=7,SUM('Tangible Benefits'!$H$12,'Tangible Benefits'!$H$13,'Tangible Benefits'!$H$14,'Tangible Benefits'!$H$15,'Tangible Benefits'!$H$16,'Tangible Benefits'!$H$17,'Tangible Benefits'!$H$18),"") | K19: TOTAL | Q19: =IF(COUNT('Tangible Benefits'!$Q$12,'Tangible Benefits'!$Q$13,'Tangible Benefits'!$Q$14,'Tangible Benefits'!$Q$15,'Tangible Benefits'!$Q$16,'Tangible Benefits'!$Q$17)=6,SUM('Tangible Benefits'!$Q$12,'Tangible Benefits'!$Q$13,'Tangible Benefits'!$Q$14,'Tangible Benefits'!$Q$15,'Tangible Benefits'!$Q$16,'Tangible Benefits'!$Q$17),"")
C21: Supplies Cost Reduction = Total Supplies of the Existing System − Total Supplies of the Proposed System
C22: Supplies Cost Reduction | P22: =IF(COUNT('Tangible Benefits'!$H$19,'Tangible Benefits'!$Q$19)=2,'Tangible Benefits'!$H$19-'Tangible Benefits'!$Q$19,"")
C24: B. LABOR COST
C26: EXISTING SYSTEM | K26: PROPOSED SYSTEM
C27: Personnel | E27: Salary/ Month | G27: Annual | K27: Personnel | M27: Salary/ Month | O27: Annual
C28: Inventory personnel | G28: =IF(ISNUMBER('Tangible Benefits'!$E$28),'Tangible Benefits'!$E$28*12,"") | K28: Inventory personnel | O28: =IF(ISNUMBER('Tangible Benefits'!$M$28),'Tangible Benefits'!$M$28*12,"")
C29: Reporting personnel | G29: =IF(ISNUMBER('Tangible Benefits'!$E$29),'Tangible Benefits'!$E$29*12,"") | K29: Reporting personnel | O29: =IF(ISNUMBER('Tangible Benefits'!$M$29),'Tangible Benefits'!$M$29*12,"")
C30: Accountability personnel | G30: =IF(ISNUMBER('Tangible Benefits'!$E$30),'Tangible Benefits'!$E$30*12,"") | K30: Accountability personnel | O30: =IF(ISNUMBER('Tangible Benefits'!$M$30),'Tangible Benefits'!$M$30*12,"")
C31: TOTAL | G31: =IF(COUNT('Tangible Benefits'!$G$28,'Tangible Benefits'!$G$29,'Tangible Benefits'!$G$30)=3,SUM('Tangible Benefits'!$G$28,'Tangible Benefits'!$G$29,'Tangible Benefits'!$G$30),"") | K31: TOTAL | O31: =IF(COUNT('Tangible Benefits'!$O$28,'Tangible Benefits'!$O$29,'Tangible Benefits'!$O$30)=3,SUM('Tangible Benefits'!$O$28,'Tangible Benefits'!$O$29,'Tangible Benefits'!$O$30),"")
C33: Labor Cost Reduction = Labor Cost of the Existing System − Labor Cost of the Proposed System
C34: Labor Cost Reduction | P34: =IF(COUNT('Tangible Benefits'!$G$31,'Tangible Benefits'!$O$31)=2,'Tangible Benefits'!$G$31-'Tangible Benefits'!$O$31,"")
C36: Total Cost Reduction = Labor Cost Reduction + Supplies Cost Reduction
C37: Total Cost Reduction | P37: =IF(COUNT('Tangible Benefits'!$P$34,'Tangible Benefits'!$P$22)=2,SUM('Tangible Benefits'!$P$34,'Tangible Benefits'!$P$22),"")
B40: This table follows the Breakdown of Tangible Benefit Worksheet in the supplied reference. Annual supplies cost reduction and labor cost reduction remain blank because the green company inventory table provides no supplies spending, salaries or staffing figures. A reduction in employee headcount or payroll has not been assumed.
B42: The 463 units shown as missing or without reports identify an equipment reconciliation concern. Their monetary value and any equipment-related savings remain blank because replacement prices and confirmed loss or recovery records were not supplied.
B44: IT303: SYSTEMS ANALYSIS AND DESIGN | S44: 3

Sheet Company Inventory
B2: HAND TOOLS AND OTHERS MONITORING
B4: ITEM NO. | C4: POWER TOOLS | D4: QTY. | E4: NEED TO COMPLY | F4: MISSING OR NO REPORT
B5: 1 | C5: SHOVEL (PALA, LAPAD) | D5: 19
B6: 2 | C6: SHOVEL (PALA, BILOG) | D6: 23 | E6: 42 | F6: 19
B7: 3 | C7: BARETA | D7: 13
B8: 4 | C8: ITAK | D8: 4
B9: 5 | C9: PIKO | D9: 4
B10: 6 | C10: PLASTIC DRUM 200L | D10: 14
B11: 7 | C11: IBC WATER TANK 1000L | D11: 5
B12: 8 | C12: WHEEL BARROW | D12: 4
B13: 9 | C13: OXYGEN TANK | D13: 3
B14: 10 | C14: GAS TANK | D14: 5
B15: 11 | C15: ELECTRIC KETTLE | D15: 2
B16: 12 | C16: EXTENSION | D16: 10
B17: 13 | C17: DOUBLE BURNER STOVE | D17: 8
B18: 14 | C18: LABABO | D18: 5
... B20: 16 | C20: GARDEN HOSE | D20: 5
B21: 17 | C21: GI PIPES | D21: 225 | E21: 300 | F21: 75
B22: 18 | C22: BASE JACK | D22: 27
B23: 19 | C23: U-JACK | D23: 56
B24: 20 | C24: BUCKETS | D24: 39
B25: 21 | C25: CATWALK FLATFORM SCAFFOLDING | D25: 33
B26: 22 | C26: H-FRAME SCAFFOLDING | D26: 64
B27: 23 | C27: BRACES SCAFFOLDING | D27: 41
B28: 24 | C28: WATER-PUMP | D28: 2
B29: 25 | C29: GARDEN SPRINKLER | D29: 2
B30: 26 | C30: SWIVEL CLAMP | D30: 141 | E30: 510 | F30: 369
B31: 27
B33: SOURCE CHECK: 26 populated categories; 758 recorded units; 463 missing or unreported units.
B35: Blank cells are retained as blanks. Only three categories have supplied requirements and reported gaps. The 463 units are not automatically confirmed physical losses. “CATWALK FLATFORM SCAFFOLDING” preserves the spelling in the green source image.
B37: Source: user-supplied green “HAND TOOLS AND OTHERS MONITORING” image. Application records are demonstration data and are excluded.
B39: COMPANY DATA SOURCE: GREEN INVENTORY TABLE ONLY | H39: 4

Sheet Input Details
B2: SUPPORTING INPUTS — LEAVE UNKNOWN VALUES BLANK
B4: These inputs complete quantities omitted from the reference layout. They are not supplied by the green company inventory table. No value or development duration is assumed.
B6: Input | C6: Value | D6: Unit / purpose
B7: Training delivery duration | D7: days
B8: Database server quantity | D8: items / services
B9: External drive quantity | D9: items
B10: Software / vendor platform quantity | D10: licenses / packages
B12: Financial inputs on all sheets are intentionally blank. For labor, enter the combined monthly cost for the personnel group shown, rather than assuming any employee count. Annualization uses 12 months as a unit conversion. Time saved does not automatically reduce payroll.
